README.md
setup.py
pulumi_twingate/__init__.py
pulumi_twingate/_inputs.py
pulumi_twingate/_utilities.py
pulumi_twingate/get_twingate_connector.py
pulumi_twingate/get_twingate_connectors.py
pulumi_twingate/get_twingate_dns_filtering_profile.py
pulumi_twingate/get_twingate_group.py
pulumi_twingate/get_twingate_groups.py
pulumi_twingate/get_twingate_remote_network.py
pulumi_twingate/get_twingate_remote_networks.py
pulumi_twingate/get_twingate_resource.py
pulumi_twingate/get_twingate_resources.py
pulumi_twingate/get_twingate_security_policies.py
pulumi_twingate/get_twingate_security_policy.py
pulumi_twingate/get_twingate_service_accounts.py
pulumi_twingate/get_twingate_user.py
pulumi_twingate/get_twingate_users.py
pulumi_twingate/outputs.py
pulumi_twingate/provider.py
pulumi_twingate/pulumi-plugin.json
pulumi_twingate/py.typed
pulumi_twingate/twingate_connector.py
pulumi_twingate/twingate_connector_tokens.py
pulumi_twingate/twingate_dns_filtering_profile.py
pulumi_twingate/twingate_group.py
pulumi_twingate/twingate_remote_network.py
pulumi_twingate/twingate_resource.py
pulumi_twingate/twingate_service_account.py
pulumi_twingate/twingate_service_account_key.py
pulumi_twingate/twingate_user.py
pulumi_twingate.egg-info/PKG-INFO
pulumi_twingate.egg-info/SOURCES.txt
pulumi_twingate.egg-info/dependency_links.txt
pulumi_twingate.egg-info/not-zip-safe
pulumi_twingate.egg-info/requires.txt
pulumi_twingate.egg-info/top_level.txt
pulumi_twingate/config/__init__.py
pulumi_twingate/config/outputs.py
pulumi_twingate/config/vars.py