Metadata-Version: 2.1
Name: pulumi-twingate
Version: 3.3.1
Summary: A Pulumi package for creating and managing Twingate cloud resources.
Home-page: https://www.twingate.com
License: Apache-2.0
Project-URL: Repository, https://github.com/Twingate/pulumi-twingate
Keywords: pulumi twingate category/infrastructure
Platform: UNKNOWN
Requires-Python: >=3.9
